{
  "hi:Start": "शुरू करें",
  "hi:Today.": "आज।",
  "hi:Lead": "नेतृत्व करें",
  "hi:Tomorrow.": "कल।",
  "hi:Why today can’t wait": "क्यों आज इंतजार नहीं कर सकता",
  "hi:The scale of": "का पैमाना",
  "hi:the crisis.": "संकट।",
  "hi:1.6°C above pre-industrial levels. 2024 was the warmest year in 175 years of recorded history.": "पूर्व-औद्योगिक स्तर से 1.6°C ऊपर। 2024 दर्ज इतिहास के 175 वर्षों में सबसे गर्म वर्ष था।",
  "hi:The environmental crisis is already reaching business balance sheets —": "पर्यावरण संकट पहले से ही व्यावसायिक बैलेंस शीट तक पहुंच रहा है —",
  "hi:$38 trillion": "$38 ट्रिलियन",
  "hi:in global GDP is at risk by 2050.": "2050 तक वैश्विक सकल घरेलू उत्पाद जोखिम में है।",
  "hi:Those who start today — will lead tomorrow.": "जो आज शुरू करेंगे — वे कल नेतृत्व करेंगे।",
  "gu:Why today can’t wait": "કેમ આજે રાહ જોઈ શકતા નથી",
  "gu:The scale of": "નું માપ",
  "gu:the crisis.": "સંકટ.",
  "gu:1.6°C above pre-industrial levels. 2024 was the warmest year in 175 years of recorded history.": "પૂર્વ-ઔદ્યોગિક સ્તરોથી 1.6°C ઉપર. 2024 એ નોંધાયેલા ઇતિહાસના 175 વર્ષોમાં સૌથી ગરમ વર્ષ હતું.",
  "gu:The environmental crisis is already reaching business balance sheets —": "પર્યાવરણીય સંકટ પહેલાથી જ બિઝનેસ બેલેન્સ શીટ સુધી પહોંચી રહ્યું છે —",
  "gu:$38 trillion": "$38 ટ્રિલિયન",
  "gu:in global GDP is at risk by 2050.": "2050 સુધીમાં વૈશ્વિક જીડીપી જોખમમાં છે.",
  "gu:Those who start today — will lead tomorrow.": "જેઓ આજે શરૂ કરશે — તેઓ આવતીકાલે નેતૃત્વ કરશે.",
  "hi:°C": "°C",
  "gu:°C": "°C",
  "hi:T": " ट्रिलियन",
  "gu:T": " ટ્રિલિયન",
  "hi:$": "₹",
  "gu:$": "રૂ. ",
  "hi:1.6°C": "1.6°C",
  "hi:$38T": "₹38 ट्रिलियन",
  "gu:$38T": "રૂ. 38 ટ્રિલિયન",
  "hi:Above pre-industrial levels (2024)": "पूर्व-औद्योगिक स्तर से ऊपर (2024)",
  "hi:Total global GDP risk by 2050": "2050 तक कुल वैश्विक सकल घरेलू उत्पाद जोखिम",
  "hi:Assurance-ready disclosures across BRSR, GRI, and TCFD. We refine your sustainability narrative for global investors.": "BRSR, GRI और TCFD में आश्वासन-तैयार खुलासे। हम वैश्विक निवेशकों के लिए आपके स्थिरता विवरण को परिष्कृत करते हैं।",
  "hi:High-precision carbon accounting and Net-Zero engineering. We guide enterprises through CBAM advisory.": "उच्च-सटीक कार्बन लेखांकन और नेट-जीरो इंजीनियरिंग। हम CBAM परामर्श के माध्यम से उद्यमों का मार्गदर्शन करते हैं।",
  "hi:Performance benchmarking for global ratings. We manage SBTi target setting and assessment optimization.": "वैश्विक रेटिंग के लिए प्रदर्शन बेंचमार्किंग। हम SBTi लक्ष्य निर्धारण और मूल्यांकन अनुकूलन का प्रबंधन करते हैं।",
  "hi:Flawless execution of SPCB/SPCB mandates. We secure Clearances and conduct robust impact studies.": "SPCB/SPCB जनादेश का निर्दोष निष्पादन। हम मंजूरी सुरक्षित करते हैं और मजबूत प्रभाव अध्ययन करते हैं।",
  "hi:Strategic EPR management. We handle waste management licenses across Plastic, E-waste, and Hazardous categories.": "रणनीतिक ईपीआर प्रबंधन। हम प्लास्टिक, ई-कचरा और खतरनाक श्रेणियों में अपशिष्ट प्रबंधन लाइसेंस संभालते हैं।",
  "hi:Implementation of world-class EHS standards. We ensure certification readiness and ongoing system audits.": "विश्व स्तरीय ईएचएस मानकों का कार्यान्वयन। हम प्रमाणन तत्परता और निरंतर सिस्टम ऑडिट सुनिश्चित करते हैं।"
}